commonocean/__init__.py
commonocean/common/__init__.py
commonocean/common/file_reader.py
commonocean/common/file_writer.py
commonocean/common/solution.py
commonocean/planning/__init__.py
commonocean/planning/goal.py
commonocean/planning/planning_problem.py
commonocean/prediction/__init__.py
commonocean/prediction/prediction.py
commonocean/scenario/__init__.py
commonocean/scenario/obstacle.py
commonocean/scenario/scenario.py
commonocean/scenario/state.py
commonocean/scenario/traffic_sign.py
commonocean/scenario/trajectory.py
commonocean/scenario/waters.py
commonocean/visualization/MPRenderer.py
commonocean/visualization/__init__.py
commonocean/visualization/draw_dispatch_cr.py
commonocean/visualization/drawable.py
commonocean/visualization/param_server.py
commonocean/visualization/planning.py
commonocean/visualization/renderer.py
commonocean/visualization/scenario.py
commonocean/visualization/testings.py
commonocean/visualization/traffic_sign.py
commonocean/visualization/util.py
commonocean/visualization/traffic_signs/101.png
commonocean/visualization/traffic_signs/102.png
commonocean/visualization/traffic_signs/103.png
commonocean/visualization/traffic_signs/104.png
commonocean/visualization/traffic_signs/105.png
commonocean/visualization/traffic_signs/106.png
commonocean/visualization/traffic_signs/107.png
commonocean_io-2025.1.dist-info/licenses/LICENSE
commonocean_io-2025.1.dist-info/METADATA
commonocean_io-2025.1.dist-info/WHEEL
commonocean_io-2025.1.dist-info/top_level.txt
commonocean_io-2025.1.dist-info/RECORD
