Metadata-Version: 2.4
Name: commonocean-io
Version: 2025.1
Summary: Python tool to read, write, and visualize CommonOcean scenarios and solutions for automated vessels.
Author: Cyber-Physical Systems Group, Technical University of Munich
Author-email: commonocean@lists.lrz.de
License: GNU General Public License v3.0
Keywords: autonomous vessels motion planning
Classifier: Programming Language :: Python :: 3.8
Classifier: Programming Language :: Python :: 3.9
Classifier: Programming Language :: Python :: 3.10
Classifier: License :: OSI Approved :: GNU General Public License v3 (GPLv3)
Classifier: Operating System :: POSIX :: Linux
Classifier: Operating System :: MacOS
Classifier: Operating System :: Microsoft :: Windows
License-File: LICENSE
Requires-Dist: commonocean-vessel-models==1.0.0
Requires-Dist: commonroad-io==2023.1
Requires-Dist: matplotlib~=3.6.0
Requires-Dist: numpy~=1.24.0
Requires-Dist: imageio~=2.9.0
Requires-Dist: setuptools>=42.0.1
Requires-Dist: lxml>=4.2.2
Requires-Dist: iso3166>=1.0.1
Provides-Extra: doc
Requires-Dist: sphinx; extra == "doc"
Requires-Dist: sphinx_rtd_theme==2.0.0; extra == "doc"
Provides-Extra: tests
Requires-Dist: pytest~=8.0.0; extra == "tests"
Dynamic: author
Dynamic: author-email
Dynamic: classifier
Dynamic: description
Dynamic: description-content-type
Dynamic: keywords
Dynamic: license
Dynamic: license-file
Dynamic: provides-extra
Dynamic: requires-dist
Dynamic: summary
